homework/hw04/q02/leq.v
/*          OPCODE SRC  DST  IMMDATA */
myROM[0] = {movi, RXX, Rg0, 4'b0111};
myROM[1] = {movi,  RXX, Rg1, 4'b0010};
myROM[2] = {mov,  Rg0, Rg2, 4'b0000};
myROM[3] = {cmp,  Rg1, Rg2, 4'b0000};
myROM[4] = {jz,  RXX, Rg2, 4'b0101}; 
myROM[5] = {cmpi,  RXX, Rg2, 4'b0000};
myROM[6] = {jz,  RXX, RXX, 4'b0101}; 
myROM[7] = {addi,  RXX, Rg2, 4'b0001};
myROM[8] = {jmp,  RXX, RXX, 4'b1011}; 
myROM[9] = {movi,  RXX, Rg2, 4'b0001};
myROM[10] = {jmp,  RXX, RXX, 4'b0000};
myROM[11] = {movi,  RXX, Rg2, 4'b0000};
myROM[12] = {jmp,  RXX, RXX, 4'b0000};
myROM[13] = {jmp,  RXX, RXX, 4'b0000};
myROM[14] = {jmp,  RXX, RXX, 4'b0000};
myROM[15] = {jmp,  RXX, RXX, 4'b0000};

/*
Expected output:

Final state of register file:
    r0= 7
    r1= 2
    r2= 0
    r3= x

*/

homework/hw04/q02/modE15Process.v
module E15Process(input clk);

   // Register names
   parameter 
      Rg0 = 2'b00, Rg1 = 2'b01,
      Rg2 = 2'b10, Rg3 = 2'b11, 
      RXX = 2'b00;

   // Opcodes
   parameter
     jmp  = 4'b0000, jz   = 4'b0010,
     movi = 4'b1001, mov  = 4'b1000,
     addi = 4'b1011, add  = 4'b1010,
     subi = 4'b1101, sub  = 4'b1100,
     cmpi = 4'b1111, cmp  = 4'b1110,
     jnz  = 4'b0011;
   

   /*Processor state (actual values) */
   reg [3:0] pc;             // Program Counter
   reg       zFlag;          // Zero flag
   reg [3:0] r0, r1, r2, r3; // Registers


   /*Program storage*/
   reg [11:0] myROM [15:0]; // ROM (holds program)

   initial
     begin

        `include "leq.v"   // load the program
        
        pc = 4'b0000;           // initialize the program counter
        
     end


   /*Parts of the instruction*/
   wire [3:0] opCode;         // op code
   wire [1:0] src, dst;       // src and dst register
   wire [3:0] immData;        // "Immediate" data


   wire [3:0] pcIncr; // Program Counter Increment
   wire [3:0] pcRes;  // Output of pc ALU
   wire       pcz;    // Unused - zero flag for pc ALU
   
   wire [3:0] storeVal, operand1, operand2;

   /*ALU wires*/
   wire       addNotSub; // Determines if ALU adds or subtracts
   wire [3:0] aluOutput;    // Output (combinational) of ALU
   wire       aluOutputZero;      // Output (combinational) of ALU zero flag


   
   assign {opCode, src, dst, immData} = myROM[pc];
   assign addNotSub = ((opCode == add) | (opCode == addi));


   /*
   pcIncr is a 4-bit value representing the value
   that is to be added to the program counter
   logic: if jmp, then immData, else if jz and zFlag, 
            then immData, else if jnz and not zFlag, 
            then immData, else 1  
   */
   assign pcIncr = (opCode == jmp) ? immData :
                    (opCode == jz)  ? (zFlag ? immData : 4'b0001) :
                    (opCode == jnz) ? (zFlag ? 4'b0001 : immData) : 
                    4'b0001;
  
   /*
   storeVal is a 4-bit value representing the value that
   is to be stored in the destination register, for
   instructions that write to it
   logic: If mov, then src (0 if RXX)), 
          else if movi, then immData 
          else aluOutput
   */
   assign storeVal = (opCode == mov) ? (src == Rg0) ? r0 :
                                        (src == Rg1) ? r1 :
                                        (src == Rg2) ? r2 :
                                        (src == Rg3) ? r3 : 4'bz :
                      (opCode == movi) ? immData : aluOutput;
   
   /* 
   operand1 is a 4-bit value representing the first operand
   to be passed into the ALU
   logic: If addi, subi, cmpi, then immData
          else if src is Rg0, then r0
          else if src is Rg1, then r1
          else if src is Rg2, then r2
          else if src is Rg3, then r3
          else 0 (RXX)
   */
   assign operand1 = (opCode == addi | opCode == subi | opCode == cmpi) ? immData :
                     (src == Rg0) ? r0 :
                     (src == Rg1) ? r1 :
                     (src == Rg2) ? r2 :
                     (src == Rg3) ? r3 : 4'bz; 
   
   /*
   operand1 is a 4-bit value representing the second operand
   to be passed into the ALU
   logic: If dst is Rg0, then r0
          else if dst is Rg1, then r1
          else if dst is Rg2, then r2
          else if dst is Rg3, then r3
          else 0 (RXX)
   */
   assign operand2 = (dst == Rg0) ? r0 :
                     (dst == Rg1) ? r1 :
                     (dst == Rg2) ? r2 :
                     (dst == Rg3) ? r3 : 4'bz;

   always @(posedge clk)
      begin 

        // Update zero flag
        case(opCode)
          addi, add, subi, sub, cmpi, cmp:
            begin
               zFlag <= aluOutputZero; // taken care of by dataALU
            end
        endcase

        // update destination register
        case(opCode)
          movi, mov, add, addi, sub, subi:
            case(dst) // switch statement, will store storeVal in appropriate register
              Rg0: r0 <= storeVal;
              Rg1: r1 <= storeVal;
              Rg2: r2 <= storeVal;
              Rg3: r3 <= storeVal;
            endcase
        endcase

        // Update program counter
        pc <= pcRes; // taken care of by pcALU
 
     end

   // inputs/outputs:        add/sub, operand1, operand2, zero flag, operation result
   simpleALU dataALU(addNotSub, operand1, operand2, aluOutputZero, aluOutput);
   // input is always add
   simpleALU pcALU(1'b1, pc, pcIncr, pcz, pcRes);

endmodule


module simpleALU(
    input addNotSub,
    input [3:0] src, dst,
    output zFlag,
    output [3:0] res);
    wire Cout;

    fourbit_adder the_adder(dst, addNotSub ? src : ~src, ~addNotSub, res, Cout);

    assign zFlag = !(res);

endmodule

module fourbit_adder(A,B, Cin, S, Cout);

    input [3:0] A;
    input [3:0] B;
    input Cin;
    output[3:0] S;
    output Cout;

    wire temp0, temp1, temp2;

    full_adder_nodelay first(A[0], B[0], Cin, S[0], temp0);
    full_adder_nodelay second(A[1], B[1], temp0, S[1], temp1);
    full_adder_nodelay third(A[2], B[2], temp1, S[2], temp2);
    full_adder_nodelay fourth(A[3], B[3], temp2, S[3], Cout);

endmodule

module full_adder_nodelay(A, B, Cin, S, Cout);

    input A, B, Cin;
    output S, Cout;

    assign S = A ^ B ^ Cin;
    assign Cout = (A & B) | (A & Cin) | (B & Cin);

endmodule



//ra0Eequ6ucie6Jei0koh6phishohm9

homework/hw04/q04/E15Process_tb.v
`timescale 1ns/100ps
`default_nettype none
`include "modE15Process.v"

module E15Process_TB;

   reg clk = 0;


   E15Process proc(clk);

   always #3
     clk = ~clk;

   initial begin
      $dumpfile("E15Process_tb.vcd");
      $dumpvars(0, E15Process_TB);
      #1000

      $display("Final state of register file:\n\tr0=%d\n\tr1=%d\n\tr2=%d\n\tr3=%d", 
          proc.r0, proc.r1, proc.r2, proc.r3);

      $finish;
   end

endmodule // E15Process_TB

homework/hw04/q02/E15Process_tb.vcd
$date
	Sun Oct  1 02:44:53 2023
$end
$version
	Icarus Verilog
$end
$timescale
	100ps
$end
$scope module E15Process_TB $end
$var reg 1 ! clk $end
$scope module proc $end
$var wire 1 " addNotSub $end
$var wire 1 ! clk $end
$var wire 4 # storeVal [3:0] $end
$var wire 2 $ src [1:0] $end
$var wire 1 % pcz $end
$var wire 4 & pcRes [3:0] $end
$var wire 4 ' pcIncr [3:0] $end
$var wire 4 ( operand2 [3:0] $end
$var wire 4 ) operand1 [3:0] $end
$var wire 4 * opCode [3:0] $end
$var wire 4 + immData [3:0] $end
$var wire 2 , dst [1:0] $end
$var wire 1 - aluOutputZero $end
$var wire 4 . aluOutput [3:0] $end
$var parameter 2 / RXX $end
$var parameter 2 0 Rg0 $end
$var parameter 2 1 Rg1 $end
$var parameter 2 2 Rg2 $end
$var parameter 2 3 Rg3 $end
$var parameter 4 4 add $end
$var parameter 4 5 addi $end
$var parameter 4 6 cmp $end
$var parameter 4 7 cmpi $end
$var parameter 4 8 jmp $end
$var parameter 4 9 jnz $end
$var parameter 4 : jz $end
$var parameter 4 ; mov $end
$var parameter 4 < movi $end
$var parameter 4 = sub $end
$var parameter 4 > subi $end
$var reg 4 ? pc [3:0] $end
$var reg 4 @ r0 [3:0] $end
$var reg 4 A r1 [3:0] $end
$var reg 4 B r2 [3:0] $end
$var reg 4 C r3 [3:0] $end
$var reg 1 D zFlag $end
$scope module dataALU $end
$var wire 1 " addNotSub $end
$var wire 4 E dst [3:0] $end
$var wire 4 F src [3:0] $end
$var wire 1 - zFlag $end
$var wire 4 G res [3:0] $end
$var wire 1 H Cout $end
$scope module the_adder $end
$var wire 4 I A [3:0] $end
$var wire 4 J B [3:0] $end
$var wire 1 K Cin $end
$var wire 1 L temp2 $end
$var wire 1 M temp1 $end
$var wire 1 N temp0 $end
$var wire 4 O S [3:0] $end
$var wire 1 H Cout $end
$scope module first $end
$var wire 1 P A $end
$var wire 1 Q B $end
$var wire 1 K Cin $end
$var wire 1 N Cout $end
$var wire 1 R S $end
$upscope $end
$scope module fourth $end
$var wire 1 S A $end
$var wire 1 T B $end
$var wire 1 H Cout $end
$var wire 1 U S $end
$var wire 1 L Cin $end
$upscope $end
$scope module second $end
$var wire 1 V A $end
$var wire 1 W B $end
$var wire 1 N Cin $end
$var wire 1 M Cout $end
$var wire 1 X S $end
$upscope $end
$scope module third $end
$var wire 1 Y A $end
$var wire 1 Z B $end
$var wire 1 M Cin $end
$var wire 1 L Cout $end
$var wire 1 [ S $end
$upscope $end
$upscope $end
$upscope $end
$scope module pcALU $end
$var wire 1 \ addNotSub $end
$var wire 4 ] dst [3:0] $end
$var wire 4 ^ src [3:0] $end
$var wire 1 % zFlag $end
$var wire 4 _ res [3:0] $end
$var wire 1 ` Cout $end
$scope module the_adder $end
$var wire 4 a A [3:0] $end
$var wire 4 b B [3:0] $end
$var wire 1 c Cin $end
$var wire 1 d temp2 $end
$var wire 1 e temp1 $end
$var wire 1 f temp0 $end
$var wire 4 g S [3:0] $end
$var wire 1 ` Cout $end
$scope module first $end
$var wire 1 h A $end
$var wire 1 i B $end
$var wire 1 c Cin $end
$var wire 1 f Cout $end
$var wire 1 j S $end
$upscope $end
$scope module fourth $end
$var wire 1 k A $end
$var wire 1 l B $end
$var wire 1 ` Cout $end
$var wire 1 m S $end
$var wire 1 d Cin $end
$upscope $end
$scope module second $end
$var wire 1 n A $end
$var wire 1 o B $end
$var wire 1 f Cin $end
$var wire 1 e Cout $end
$var wire 1 p S $end
$upscope $end
$scope module third $end
$var wire 1 q A $end
$var wire 1 r B $end
$var wire 1 e Cin $end
$var wire 1 d Cout $end
$var wire 1 s S $end
$upscope $end
$upscope $end
$upscope $end
$upscope $end
$upscope $end
$enddefinitions $end
$comment Show the parameter values. $end
$dumpall
b1101 >
b1100 =
b1001 <
b1000 ;
b10 :
b11 9
b0 8
b1111 7
b1110 6
b1011 5
b1010 4
b11 3
b10 2
b1 1
b0 0
b0 /
$end
#0
$dumpvars
0s
0r
0q
0p
0o
0n
0m
0l
0k
1j
0i
1h
b1 g
0f
0e
0d
0c
b0 b
b1 a
0`
b1 _
b0 ^
b1 ]
1\
x[
xZ
xY
xX
xW
xV
xU
xT
xS
xR
xQ
xP
bx O
xN
xM
xL
1K
bx J
bx I
xH
bx G
bx F
bx E
xD
bx C
bx B
bx A
bx @
b0 ?
bx .
x-
b0 ,
b111 +
b1001 *
bx )
bx (
b1 '
b1 &
0%
b0 $
b111 #
0"
0!
$end
#30
1p
0Q
0W
0Z
1T
xN
1f
b1000 J
b10 #
0%
b10 &
b10 _
b10 g
0j
b111 )
b111 F
xP
xV
xY
xS
b1 ,
b10 +
1i
bx (
bx E
bx I
b1 b
b1 ?
b1 ^
b111 @
1!
#60
0!
#90
xM
xN
xL
x-
bx .
bx G
bx O
xR
0f
0s
1j
0%
b11 &
b11 _
b11 g
1p
0e
xP
xV
xY
xS
b111 #
bx (
bx E
bx I
b1000 *
b10 ,
b0 +
0i
1o
b10 b
b10 ?
b10 ^
b10 A
1!
#120
0!
#150
1H
1[
0U
1M
1L
0-
0X
1s
1N
1Q
1Z
1e
b101 .
b101 G
b101 O
1R
b1101 J
0%
0p
1f
1P
1V
1Y
0S
b10 )
b10 F
b100 &
b100 _
b100 g
0j
b111 (
b111 E
b111 I
b101 #
b1110 *
b1 $
1i
b11 b
b11 ?
b11 ^
b111 B
1!
#180
0!
#210
b0 #
1-
0R
b0 .
b0 G
b0 O
0[
0Q
0Z
b1000 J
0f
0m
b111 )
b111 F
1j
0p
0e
0%
b101 &
b101 _
b101 g
1s
0d
b10 *
b0 $
b101 +
0i
0o
1r
b100 b
b100 ?
b100 ^
0D
1!
#240
0!
#270
b111 #
1R
1X
0-
b111 .
b111 G
b111 O
1[
1Q
1W
1Z
b1111 J
1p
1f
b0 )
b0 F
b110 &
b110 _
b110 g
0j
b1111 *
b0 +
1i
b101 b
b101 ?
b101 ^
1!
#300
0!
#330
b0 #
1-
0X
0R
b0 .
b0 G
b0 O
0[
0W
0m
0Q
0Z
0d
b1000 J
0f
1s
1j
b111 &
b111 _
b111 g
1p
0e
b111 )
b111 F
b10 *
b0 ,
b101 +
0i
1o
b110 b
b110 ?
b110 ^
1!
#360
0!
#390
1L
1M
1m
1d
0%
0s
b1000 #
1N
0H
1e
0X
0[
1U
0p
0-
b1000 .
b1000 G
b1000 O
0R
1Q
0W
0Z
0T
b1 )
b1 F
1f
0K
b1 J
1P
1V
1Y
0S
b1000 &
b1000 _
b1000 g
0j
1"
b111 (
b111 E
b111 I
b1011 *
b10 ,
b1 +
1i
b111 b
b111 ?
b111 ^
1!
#420
0!
#450
1-
b0 #
0X
0[
0U
1H
b0 .
b0 G
b0 O
0R
0Q
0W
0Z
1T
0f
1K
1n
1k
b1000 J
1j
1p
0e
0s
0d
0%
b11 &
b11 _
b11 g
0m
1`
0"
b1011 '
b1011 ]
b1011 a
b111 )
b111 F
b0 *
b0 ,
b1011 +
0i
0o
0r
1l
b1000 b
b1000 ?
b1000 ^
b1000 B
1!
#480
0!
#510
b110 #
1Q
1Z
1N
0M
0L
b1101 J
0R
1X
1[
0-
b110 .
b110 G
b110 O
0U
1s
1f
1e
0`
b10 )
b10 F
0P
0V
0Y
1S
0n
0k
0j
0p
b100 &
b100 _
b100 g
0m
b1000 (
b1000 E
b1000 I
b1 '
b1 ]
b1 a
b1110 *
b1 $
b10 ,
b0 +
1i
1o
0l
b11 b
b11 ?
b11 ^
1!
#540
0!
#570
b1 #
0X
1R
0N
b1 .
b1 G
b1 O
0[
0Q
0Z
b1000 J
0f
0m
b111 )
b111 F
1j
0p
0e
0%
b101 &
b101 _
b101 g
1s
0d
b10 *
b0 $
b101 +
0i
0o
1r
b100 b
b100 ?
b100 ^
1!
#600
0!
#630
1U
1L
0-
1M
b1000 #
0R
1N
0X
b1000 .
b1000 G
b1000 O
0[
1Q
1W
1Z
b1111 J
1p
1f
b0 )
b0 F
b110 &
b110 _
b110 g
0j
b1111 *
b0 +
1i
b101 b
b101 ?
b101 ^
1!
#660
0!
#690
b0 #
0W
0m
0R
0X
0[
1-
b0 .
b0 G
b0 O
0U
0Q
0Z
0d
b1000 J
0f
1s
1P
1V
1Y
0S
1j
b111 &
b111 _
b111 g
1p
0e
b111 (
b111 E
b111 I
b111 )
b111 F
b10 *
b0 ,
b101 +
0i
1o
b110 b
b110 ?
b110 ^
1!
#720
0!
#750
1m
0M
0L
1d
0%
0s
b1001 #
0N
0H
1e
0X
0[
1U
0p
0-
b1001 .
b1001 G
b1001 O
1R
1Q
0W
0Z
0T
b1 )
b1 F
1f
0K
b1 J
0P
0V
0Y
1S
b1000 &
b1000 _
b1000 g
0j
1"
b1000 (
b1000 E
b1000 I
b1011 *
b10 ,
b1 +
1i
b111 b
b111 ?
b111 ^
1!
#780
0!
#810
1-
0U
1H
0[
b0 #
1N
1M
1L
b0 .
b0 G
b0 O
0R
0Q
0W
0Z
1T
0f
1K
1n
1k
1P
1V
1Y
0S
b1000 J
1j
1p
0e
0s
0d
0%
b11 &
b11 _
b11 g
0m
1`
0"
b1011 '
b1011 ]
b1011 a
b111 (
b111 E
b111 I
b111 )
b111 F
b0 *
b0 ,
b1011 +
0i
0o
0r
1l
b1000 b
b1000 ?
b1000 ^
b1001 B
1!
#840
0!
#870
b111 #
1Q
1Z
1N
0M
0L
b1101 J
1R
1X
1[
0-
b111 .
b111 G
b111 O
0U
1s
1f
1e
0`
b10 )
b10 F
1P
0V
0Y
1S
0n
0k
0j
0p
b100 &
b100 _
b100 g
0m
b1001 (
b1001 E
b1001 I
b1 '
b1 ]
b1 a
b1110 *
b1 $
b10 ,
b0 +
1i
1o
0l
b11 b
b11 ?
b11 ^
1!
#900
0!
#930
b10 #
0R
b10 .
b10 G
b10 O
0[
0Q
0Z
b1000 J
0f
0m
b111 )
b111 F
1j
0p
0e
0%
b101 &
b101 _
b101 g
1s
0d
b10 *
b0 $
b101 +
0i
0o
1r
b100 b
b100 ?
b100 ^
1!
#960
0!
#990
1U
1L
b1001 #
1R
0X
1M
b1001 .
b1001 G
b1001 O
0[
1Q
1W
1Z
b1111 J
1p
1f
b0 )
b0 F
b110 &
b110 _
b110 g
0j
b1111 *
b0 +
1i
b101 b
b101 ?
b101 ^
1!
#1020
0!
#1050
1-
b0 #
0R
0W
0m
0X
0[
b0 .
b0 G
b0 O
0U
0Q
0Z
0d
b1000 J
0f
1s
1V
1Y
0S
1j
b111 &
b111 _
b111 g
1p
0e
b111 (
b111 E
b111 I
b111 )
b111 F
b10 *
b0 ,
b101 +
0i
1o
b110 b
b110 ?
b110 ^
1!
#1080
0!
#1110
1m
0M
0L
1d
0%
0s
b1010 #
1N
0H
1e
1X
0[
1U
0p
0-
b1010 .
b1010 G
b1010 O
0R
1Q
0W
0Z
0T
b1 )
b1 F
1f
0K
b1 J
1P
0V
0Y
1S
b1000 &
b1000 _
b1000 g
0j
1"
b1001 (
b1001 E
b1001 I
b1011 *
b10 ,
b1 +
1i
b111 b
b111 ?
b111 ^
1!
#1140
0!
#1170
1-
0U
1H
0X
0[
b0 #
1L
1M
b0 .
b0 G
b0 O
0R
0Q
0W
0Z
1T
0f
1K
1n
1k
1V
1Y
0S
b1000 J
1j
1p
0e
0s
0d
0%
b11 &
b11 _
b11 g
0m
1`
0"
b1011 '
b1011 ]
b1011 a
b111 (
b111 E
b111 I
b111 )
b111 F
b0 *
b0 ,
b1011 +
0i
0o
0r
1l
b1000 b
b1000 ?
b1000 ^
b1010 B
1!
#1200
0!
#1230
b1000 #
1Q
1Z
1N
1M
1L
b1101 J
0R
0X
0[
0-
b1000 .
b1000 G
b1000 O
1U
1s
1f
1e
0`
b10 )
b10 F
0P
1V
0Y
1S
0n
0k
0j
0p
b100 &
b100 _
b100 g
0m
b1010 (
b1010 E
b1010 I
b1 '
b1 ]
b1 a
b1110 *
b1 $
b10 ,
b0 +
1i
1o
0l
b11 b
b11 ?
b11 ^
1!
#1260
0!
#1290
0M
b11 #
1X
0U
1R
0N
b11 .
b11 G
b11 O
0[
0L
0Q
0Z
b1000 J
0f
0m
b111 )
b111 F
1j
0p
0e
0%
b101 &
b101 _
b101 g
1s
0d
b10 *
b0 $
b101 +
0i
0o
1r
b100 b
b100 ?
b100 ^
1!
#1320
0!
#1350
1U
1L
b1010 #
1M
0R
1N
1X
b1010 .
b1010 G
b1010 O
0[
1Q
1W
1Z
b1111 J
1p
1f
b0 )
b0 F
b110 &
b110 _
b110 g
0j
b1111 *
b0 +
1i
b101 b
b101 ?
b101 ^
1!
#1380
0!
#1410
1-
0X
b0 #
0W
0m
0R
0[
b0 .
b0 G
b0 O
0U
0Q
0Z
0d
b1000 J
0f
1s
1P
1Y
0S
1j
b111 &
b111 _
b111 g
1p
0e
b111 (
b111 E
b111 I
b111 )
b111 F
b10 *
b0 ,
b101 +
0i
1o
b110 b
b110 ?
b110 ^
1!
#1440
0!
#1470
0M
1m
0L
1d
0%
0s
b1011 #
0N
0H
1e
1X
0[
1U
0p
0-
b1011 .
b1011 G
b1011 O
1R
1Q
0W
0Z
0T
b1 )
b1 F
1f
0K
b1 J
0P
1V
0Y
1S
b1000 &
b1000 _
b1000 g
0j
1"
b1010 (
b1010 E
b1010 I
b1011 *
b10 ,
b1 +
1i
b111 b
b111 ?
b111 ^
1!
#1500
0!
#1530
1-
0U
1H
0[
1M
b0 #
1N
1L
0X
b0 .
b0 G
b0 O
0R
0Q
0W
0Z
1T
0f
1K
1n
1k
1P
1Y
0S
b1000 J
1j
1p
0e
0s
0d
0%
b11 &
b11 _
b11 g
0m
1`
0"
b1011 '
b1011 ]
b1011 a
b111 (
b111 E
b111 I
b111 )
b111 F
b0 *
b0 ,
b1011 +
0i
0o
0r
1l
b1000 b
b1000 ?
b1000 ^
b1011 B
1!
#1560
0!
#1590
b1001 #
1Q
1Z
1N
1M
1L
b1101 J
1R
0X
0[
0-
b1001 .
b1001 G
b1001 O
1U
1s
1f
1e
0`
b10 )
b10 F
1P
1V
0Y
1S
0n
0k
0j
0p
b100 &
b100 _
b100 g
0m
b1011 (
b1011 E
b1011 I
b1 '
b1 ]
b1 a
b1110 *
b1 $
b10 ,
b0 +
1i
1o
0l
b11 b
b11 ?
b11 ^
1!
#1620
0!
#1650
b100 #
0U
0R
b100 .
b100 G
b100 O
1[
0L
0Q
0Z
b1000 J
0f
0m
b111 )
b111 F
1j
0p
0e
0%
b101 &
b101 _
b101 g
1s
0d
b10 *
b0 $
b101 +
0i
0o
1r
b100 b
b100 ?
b100 ^
1!
#1680
0!
#1710
b1011 #
1U
1R
1X
0-
b1011 .
b1011 G
b1011 O
0[
1L
1Q
1W
1Z
b1111 J
1p
1f
b0 )
b0 F
b110 &
b110 _
b110 g
0j
b1111 *
b0 +
1i
b101 b
b101 ?
b101 ^
1!
#1740
0!
#1770
1-
0X
b0 #
0R
0W
0m
0[
b0 .
b0 G
b0 O
0U
0Q
0Z
0d
b1000 J
0f
1s
1Y
0S
1j
b111 &
b111 _
b111 g
1p
0e
b111 (
b111 E
b111 I
b111 )
b111 F
b10 *
b0 ,
b101 +
0i
1o
b110 b
b110 ?
b110 ^
1!
#1800
0!
#1830
1M
1m
0L
1d
0%
0s
b1100 #
1N
0H
1e
0X
1[
1U
0p
0-
b1100 .
b1100 G
b1100 O
0R
1Q
0W
0Z
0T
b1 )
b1 F
1f
0K
b1 J
1P
1V
0Y
1S
b1000 &
b1000 _
b1000 g
0j
1"
b1011 (
b1011 E
b1011 I
b1011 *
b10 ,
b1 +
1i
b111 b
b111 ?
b111 ^
1!
#1860
0!
#1890
1-
0[
0U
1H
b0 #
0X
1L
b0 .
b0 G
b0 O
0R
0Q
0W
0Z
1T
0f
1K
1n
1k
1Y
0S
b1000 J
1j
1p
0e
0s
0d
0%
b11 &
b11 _
b11 g
0m
1`
0"
b1011 '
b1011 ]
b1011 a
b111 (
b111 E
b111 I
b111 )
b111 F
b0 *
b0 ,
b1011 +
0i
0o
0r
1l
b1000 b
b1000 ?
b1000 ^
b1100 B
1!
#1920
0!
#1950
b1010 #
1Q
1Z
1N
0M
1L
b1101 J
0R
1X
0[
0-
b1010 .
b1010 G
b1010 O
1U
1s
1f
1e
0`
b10 )
b10 F
0P
0V
1Y
1S
0n
0k
0j
0p
b100 &
b100 _
b100 g
0m
b1100 (
b1100 E
b1100 I
b1 '
b1 ]
b1 a
b1110 *
b1 $
b10 ,
b0 +
1i
1o
0l
b11 b
b11 ?
b11 ^
1!
#1980
0!
#2010
b101 #
0U
0X
0L
1R
0N
b101 .
b101 G
b101 O
1[
0Q
0Z
b1000 J
0f
0m
b111 )
b111 F
1j
0p
0e
0%
b101 &
b101 _
b101 g
1s
0d
b10 *
b0 $
b101 +
0i
0o
1r
b100 b
b100 ?
b100 ^
1!
#2040
0!
#2070
1M
b1100 #
1U
0-
1L
0R
1N
0X
b1100 .
b1100 G
b1100 O
1[
1Q
1W
1Z
b1111 J
1p
1f
b0 )
b0 F
b110 &
b110 _
b110 g
0j
b1111 *
b0 +
1i
b101 b
b101 ?
b101 ^
1!
#2100
0!
#2130
1-
b0 #
0[
0W
0m
0R
0X
b0 .
b0 G
b0 O
0U
0Q
0Z
0d
b1000 J
0f
1s
1P
1V
0S
1j
b111 &
b111 _
b111 g
1p
0e
b111 (
b111 E
b111 I
b111 )
b111 F
b10 *
b0 ,
b101 +
0i
1o
b110 b
b110 ?
b110 ^
1!
#2160
0!
#2190
0L
1m
0M
1d
0%
0s
b1101 #
0N
0H
1e
0X
1[
1U
0p
0-
b1101 .
b1101 G
b1101 O
1R
1Q
0W
0Z
0T
b1 )
b1 F
1f
0K
b1 J
0P
0V
1Y
1S
b1000 &
b1000 _
b1000 g
0j
1"
b1100 (
b1100 E
b1100 I
b1011 *
b10 ,
b1 +
1i
b111 b
b111 ?
b111 ^
1!
#2220
0!
#2250
1-
0U
1H
1L
b0 #
1N
1M
0[
b0 .
b0 G
b0 O
0R
0Q
0W
0Z
1T
0f
1K
1n
1k
1P
1V
0S
b1000 J
1j
1p
0e
0s
0d
0%
b11 &
b11 _
b11 g
0m
1`
0"
b1011 '
b1011 ]
b1011 a
b111 (
b111 E
b111 I
b111 )
b111 F
b0 *
b0 ,
b1011 +
0i
0o
0r
1l
b1000 b
b1000 ?
b1000 ^
b1101 B
1!
#2280
0!
#2310
b1011 #
1Q
1Z
1N
0M
1L
b1101 J
1R
1X
0[
0-
b1011 .
b1011 G
b1011 O
1U
1s
1f
1e
0`
b10 )
b10 F
1P
0V
1Y
1S
0n
0k
0j
0p
b100 &
b100 _
b100 g
0m
b1101 (
b1101 E
b1101 I
b1 '
b1 ]
b1 a
b1110 *
b1 $
b10 ,
b0 +
1i
1o
0l
b11 b
b11 ?
b11 ^
1!
#2340
0!
#2370
b110 #
0U
0L
0R
b110 .
b110 G
b110 O
1[
0Q
0Z
b1000 J
0f
0m
b111 )
b111 F
1j
0p
0e
0%
b101 &
b101 _
b101 g
1s
0d
b10 *
b0 $
b101 +
0i
0o
1r
b100 b
b100 ?
b100 ^
1!
#2400
0!
#2430
b1101 #
1U
1L
1R
0-
0X
1M
b1101 .
b1101 G
b1101 O
1[
1Q
1W
1Z
b1111 J
1p
1f
b0 )
b0 F
b110 &
b110 _
b110 g
0j
b1111 *
b0 +
1i
b101 b
b101 ?
b101 ^
1!
#2460
0!
#2490
1-
b0 #
0R
0[
0W
0m
0X
b0 .
b0 G
b0 O
0U
0Q
0Z
0d
b1000 J
0f
1s
1V
0S
1j
b111 &
b111 _
b111 g
1p
0e
b111 (
b111 E
b111 I
b111 )
b111 F
b10 *
b0 ,
b101 +
0i
1o
b110 b
b110 ?
b110 ^
1!
#2520
0!
#2550
0L
1m
0M
1d
0%
0s
b1110 #
1N
0H
1e
1X
1[
1U
0p
0-
b1110 .
b1110 G
b1110 O
0R
1Q
0W
0Z
0T
b1 )
b1 F
1f
0K
b1 J
1P
0V
1Y
1S
b1000 &
b1000 _
b1000 g
0j
1"
b1101 (
b1101 E
b1101 I
b1011 *
b10 ,
b1 +
1i
b111 b
b111 ?
b111 ^
1!
#2580
0!
#2610
1-
0U
1H
0X
1L
b0 #
1M
0[
b0 .
b0 G
b0 O
0R
0Q
0W
0Z
1T
0f
1K
1n
1k
1V
0S
b1000 J
1j
1p
0e
0s
0d
0%
b11 &
b11 _
b11 g
0m
1`
0"
b1011 '
b1011 ]
b1011 a
b111 (
b111 E
b111 I
b111 )
b111 F
b0 *
b0 ,
b1011 +
0i
0o
0r
1l
b1000 b
b1000 ?
b1000 ^
b1110 B
1!
#2640
0!
#2670
b1100 #
1Q
1Z
1N
1M
1L
b1101 J
0R
0X
1[
0-
b1100 .
b1100 G
b1100 O
1U
1s
1f
1e
0`
b10 )
b10 F
0P
1V
1Y
1S
0n
0k
0j
0p
b100 &
b100 _
b100 g
0m
b1110 (
b1110 E
b1110 I
b1 '
b1 ]
b1 a
b1110 *
b1 $
b10 ,
b0 +
1i
1o
0l
b11 b
b11 ?
b11 ^
1!
#2700
0!
#2730
0U
0L
0M
b111 #
1X
1R
0N
b111 .
b111 G
b111 O
1[
0Q
0Z
b1000 J
0f
0m
b111 )
b111 F
1j
0p
0e
0%
b101 &
b101 _
b101 g
1s
0d
b10 *
b0 $
b101 +
0i
0o
1r
b100 b
b100 ?
b100 ^
1!
#2760
0!
#2790
b1110 #
1U
1M
1L
0-
0R
1N
1X
b1110 .
b1110 G
b1110 O
1[
1Q
1W
1Z
b1111 J
1p
1f
b0 )
b0 F
b110 &
b110 _
b110 g
0j
b1111 *
b0 +
1i
b101 b
b101 ?
b101 ^
1!
#2820
0!
#2850
1-
0X
b0 #
0[
0W
0m
0R
b0 .
b0 G
b0 O
0U
0Q
0Z
0d
b1000 J
0f
1s
1P
0S
1j
b111 &
b111 _
b111 g
1p
0e
b111 (
b111 E
b111 I
b111 )
b111 F
b10 *
b0 ,
b101 +
0i
1o
b110 b
b110 ?
b110 ^
1!
#2880
0!
#2910
0L
0M
1m
1d
0%
0s
b1111 #
0N
0H
1e
1X
1[
1U
0p
0-
b1111 .
b1111 G
b1111 O
1R
1Q
0W
0Z
0T
b1 )
b1 F
1f
0K
b1 J
0P
1V
1Y
1S
b1000 &
b1000 _
b1000 g
0j
1"
b1110 (
b1110 E
b1110 I
b1011 *
b10 ,
b1 +
1i
b111 b
b111 ?
b111 ^
1!
#2940
0!
#2970
1-
0U
1H
1M
1L
b0 #
1N
0X
0[
b0 .
b0 G
b0 O
0R
0Q
0W
0Z
1T
0f
1K
1n
1k
1P
0S
b1000 J
1j
1p
0e
0s
0d
0%
b11 &
b11 _
b11 g
0m
1`
0"
b1011 '
b1011 ]
b1011 a
b111 (
b111 E
b111 I
b111 )
b111 F
b0 *
b0 ,
b1011 +
0i
0o
0r
1l
b1000 b
b1000 ?
b1000 ^
b1111 B
1!
#3000
0!
